{
  "operatorId": "DE*EBW",
  "geohash": "0DenL6Ka",
  "name": "Unknown",
  "evses": [
    {
      "id": "DEEBWE9088651",
      "connectors": [
        {
          "type": "ccs",
          "maxPowerKw": 300.0
        }
      ],
      "authMethods": null,
      "paymentMethods": null
    },
    {
      "id": "DEEBWE9088652",
      "connectors": [
        {
          "type": "ccs",
          "maxPowerKw": 300.0
        }
      ],
      "authMethods": null,
      "paymentMethods": null
    },
    {
      "id": "DEEBWE9088661",
      "connectors": [
        {
          "type": "ccs",
          "maxPowerKw": 150.0
        }
      ],
      "authMethods": null,
      "paymentMethods": null
    },
    {
      "id": "DEEBWE9088662",
      "connectors": [
        {
          "type": "ccs",
          "maxPowerKw": 150.0
        }
      ],
      "authMethods": null,
      "paymentMethods": null
    },
    {
      "id": "DEEBWE9088341",
      "connectors": [
        {
          "type": "ccs",
          "maxPowerKw": 150.0
        }
      ],
      "authMethods": null,
      "paymentMethods": null
    },
    {
      "id": "DEEBWE9088342",
      "connectors": [
        {
          "type": "ccs",
          "maxPowerKw": 150.0
        }
      ],
      "authMethods": null,
      "paymentMethods": null
    },
    {
      "id": "DEEBWE9088671",
      "connectors": [
        {
          "type": "ccs",
          "maxPowerKw": 150.0
        }
      ],
      "authMethods": null,
      "paymentMethods": null
    },
    {
      "id": "DEEBWE9088672",
      "connectors": [
        {
          "type": "ccs",
          "maxPowerKw": 150.0
        }
      ],
      "authMethods": null,
      "paymentMethods": null
    }
  ],
  "facilities": null,
  "address": {
    "city": "Wiesbaden",
    "street": "Erich-Ollenhauer-Straße",
    "houseNumber": null,
    "postcode": "65187",
    "province": null
  },
  "openingHours": {
    "isOpen247": false,
    "regularHours": [
      {
        "weekday": 1,
        "periodBegin": {
          "hour": 7,
          "minute": 0
        },
        "periodEnd": {
          "hour": 18,
          "minute": 0
        }
      },
      {
        "weekday": 2,
        "periodBegin": {
          "hour": 7,
          "minute": 0
        },
        "periodEnd": {
          "hour": 18,
          "minute": 0
        }
      },
      {
        "weekday": 3,
        "periodBegin": {
          "hour": 7,
          "minute": 0
        },
        "periodEnd": {
          "hour": 18,
          "minute": 0
        }
      },
      {
        "weekday": 4,
        "periodBegin": {
          "hour": 7,
          "minute": 0
        },
        "periodEnd": {
          "hour": 18,
          "minute": 0
        }
      },
      {
        "weekday": 5,
        "periodBegin": {
          "hour": 7,
          "minute": 0
        },
        "periodEnd": {
          "hour": 18,
          "minute": 0
        }
      },
      {
        "weekday": 6,
        "periodBegin": {
          "hour": 7,
          "minute": 0
        },
        "periodEnd": {
          "hour": 18,
          "minute": 0
        }
      }
    ]
  }
}