{
  "operatorId": "DE*EBW",
  "geohash": "0M0dYfOz",
  "name": "Unknown",
  "evses": [
    {
      "id": "DEEBWE9040511",
      "connectors": [
        {
          "type": "ccs",
          "maxPowerKw": 150.0
        }
      ],
      "authMethods": null,
      "paymentMethods": null
    },
    {
      "id": "DEEBWE9040512",
      "connectors": [
        {
          "type": "ccs",
          "maxPowerKw": 150.0
        }
      ],
      "authMethods": null,
      "paymentMethods": null
    }
  ],
  "facilities": null,
  "address": {
    "city": "Schwedt/Oder",
    "street": "Handelsstraße",
    "houseNumber": null,
    "postcode": "16303",
    "province": null
  },
  "openingHours": {
    "isOpen247": true,
    "regularHours": null
  }
}