{
  "operatorId": "DE*EBW",
  "geohash": "0C356dcH",
  "name": "Unknown",
  "evses": [
    {
      "id": "DEEBWE9052041",
      "connectors": [
        {
          "type": "unknown",
          "maxPowerKw": 3.7
        },
        {
          "type": "type2",
          "maxPowerKw": 22.0
        }
      ],
      "authMethods": null,
      "paymentMethods": null
    },
    {
      "id": "DEEBWE9052042",
      "connectors": [
        {
          "type": "unknown",
          "maxPowerKw": 3.7
        },
        {
          "type": "type2",
          "maxPowerKw": 22.0
        }
      ],
      "authMethods": null,
      "paymentMethods": null
    }
  ],
  "facilities": null,
  "address": {
    "city": "Amtzell",
    "street": "Schulstr.",
    "houseNumber": null,
    "postcode": "88279",
    "province": null
  },
  "openingHours": {
    "isOpen247": true,
    "regularHours": null
  }
}