{
  "operatorId": "DE*EBW",
  "geohash": "0JBlJ_x7",
  "name": "Unknown",
  "evses": [
    {
      "id": "DEEBWE9095481",
      "connectors": [
        {
          "type": "ccs",
          "maxPowerKw": 300.0
        }
      ],
      "authMethods": null,
      "paymentMethods": null
    },
    {
      "id": "DEEBWE9095482",
      "connectors": [
        {
          "type": "ccs",
          "maxPowerKw": 300.0
        }
      ],
      "authMethods": null,
      "paymentMethods": null
    },
    {
      "id": "DEEBWE9095242",
      "connectors": [
        {
          "type": "ccs",
          "maxPowerKw": 150.0
        }
      ],
      "authMethods": null,
      "paymentMethods": null
    },
    {
      "id": "DEEBWE9095241",
      "connectors": [
        {
          "type": "ccs",
          "maxPowerKw": 150.0
        }
      ],
      "authMethods": null,
      "paymentMethods": null
    },
    {
      "id": "DEEBWE9095181",
      "connectors": [
        {
          "type": "ccs",
          "maxPowerKw": 150.0
        }
      ],
      "authMethods": null,
      "paymentMethods": null
    },
    {
      "id": "DEEBWE9095182",
      "connectors": [
        {
          "type": "ccs",
          "maxPowerKw": 150.0
        }
      ],
      "authMethods": null,
      "paymentMethods": null
    }
  ],
  "facilities": null,
  "address": {
    "city": "Eching",
    "street": "Dieselstraße",
    "houseNumber": null,
    "postcode": "85386",
    "province": null
  },
  "openingHours": {
    "isOpen247": true,
    "regularHours": null
  }
}