{
  "operatorId": "DE*EBW",
  "geohash": "0D0s_f5l",
  "name": "Unknown",
  "evses": [
    {
      "id": "DEEBWE9051241",
      "connectors": [
        {
          "type": "ccs",
          "maxPowerKw": 300.0
        }
      ],
      "authMethods": null,
      "paymentMethods": null
    },
    {
      "id": "DEEBWE9051242",
      "connectors": [
        {
          "type": "ccs",
          "maxPowerKw": 300.0
        }
      ],
      "authMethods": null,
      "paymentMethods": null
    },
    {
      "id": "DEEBWE9051243",
      "connectors": [
        {
          "type": "chademo",
          "maxPowerKw": 50.0
        }
      ],
      "authMethods": null,
      "paymentMethods": null
    },
    {
      "id": "DEEBWE9089161",
      "connectors": [
        {
          "type": "ccs",
          "maxPowerKw": 300.0
        }
      ],
      "authMethods": null,
      "paymentMethods": null
    },
    {
      "id": "DEEBWE9089162",
      "connectors": [
        {
          "type": "chademo",
          "maxPowerKw": 50.0
        }
      ],
      "authMethods": null,
      "paymentMethods": null
    },
    {
      "id": "DEEBWE9089163",
      "connectors": [
        {
          "type": "ccs",
          "maxPowerKw": 300.0
        }
      ],
      "authMethods": null,
      "paymentMethods": null
    }
  ],
  "facilities": null,
  "address": {
    "city": "Alzenau",
    "street": "Industriegebiet Süd B",
    "houseNumber": null,
    "postcode": "63755",
    "province": null
  },
  "openingHours": {
    "isOpen247": true,
    "regularHours": null
  }
}