{
  "operatorId": "DE*EBW",
  "geohash": "0Gvy9NAB",
  "name": "Unknown",
  "evses": [
    {
      "id": "DEEBWE9044601",
      "connectors": [
        {
          "type": "ccs",
          "maxPowerKw": 150.0
        }
      ],
      "authMethods": null,
      "paymentMethods": null
    },
    {
      "id": "DEEBWE9044602",
      "connectors": [
        {
          "type": "ccs",
          "maxPowerKw": 150.0
        }
      ],
      "authMethods": null,
      "paymentMethods": null
    }
  ],
  "facilities": null,
  "address": {
    "city": "Halberstadt",
    "street": "Breiter Weg",
    "houseNumber": null,
    "postcode": "38820",
    "province": null
  },
  "openingHours": {
    "isOpen247": false,
    "regularHours": [
      {
        "weekday": 1,
        "periodBegin": {
          "hour": 9,
          "minute": 0
        },
        "periodEnd": {
          "hour": 19,
          "minute": 0
        }
      },
      {
        "weekday": 2,
        "periodBegin": {
          "hour": 9,
          "minute": 0
        },
        "periodEnd": {
          "hour": 19,
          "minute": 0
        }
      },
      {
        "weekday": 3,
        "periodBegin": {
          "hour": 9,
          "minute": 0
        },
        "periodEnd": {
          "hour": 19,
          "minute": 0
        }
      },
      {
        "weekday": 4,
        "periodBegin": {
          "hour": 9,
          "minute": 0
        },
        "periodEnd": {
          "hour": 19,
          "minute": 0
        }
      },
      {
        "weekday": 5,
        "periodBegin": {
          "hour": 9,
          "minute": 0
        },
        "periodEnd": {
          "hour": 19,
          "minute": 0
        }
      },
      {
        "weekday": 6,
        "periodBegin": {
          "hour": 9,
          "minute": 0
        },
        "periodEnd": {
          "hour": 18,
          "minute": 0
        }
      }
    ]
  }
}