{
  "operatorId": "DE*EBW",
  "geohash": "0GMCXmAQ",
  "name": "Unknown",
  "evses": [
    {
      "id": "DEEBWE9103111",
      "connectors": [
        {
          "type": "ccs",
          "maxPowerKw": 300.0
        }
      ],
      "authMethods": null,
      "paymentMethods": null
    },
    {
      "id": "DEEBWE9103112",
      "connectors": [
        {
          "type": "ccs",
          "maxPowerKw": 300.0
        }
      ],
      "authMethods": null,
      "paymentMethods": null
    },
    {
      "id": "DEEBWE9099501",
      "connectors": [
        {
          "type": "ccs",
          "maxPowerKw": 150.0
        }
      ],
      "authMethods": null,
      "paymentMethods": null
    },
    {
      "id": "DEEBWE9099502",
      "connectors": [
        {
          "type": "ccs",
          "maxPowerKw": 150.0
        }
      ],
      "authMethods": null,
      "paymentMethods": null
    },
    {
      "id": "DEEBWE9099503",
      "connectors": [
        {
          "type": "type2",
          "maxPowerKw": 22.0
        }
      ],
      "authMethods": null,
      "paymentMethods": null
    }
  ],
  "facilities": null,
  "address": {
    "city": "Velbert",
    "street": "Bonsfelder Straße",
    "houseNumber": null,
    "postcode": "42555",
    "province": null
  },
  "openingHours": {
    "isOpen247": true,
    "regularHours": null
  }
}