{
  "operatorId": "DE*EBW",
  "geohash": "0GKsTstD",
  "name": "Unknown",
  "evses": [
    {
      "id": "DEEBWE9089001",
      "connectors": [
        {
          "type": "ccs",
          "maxPowerKw": 300.0
        }
      ],
      "authMethods": null,
      "paymentMethods": null
    },
    {
      "id": "DEEBWE9089002",
      "connectors": [
        {
          "type": "ccs",
          "maxPowerKw": 300.0
        }
      ],
      "authMethods": null,
      "paymentMethods": null
    },
    {
      "id": "DEEBWE9089211",
      "connectors": [
        {
          "type": "ccs",
          "maxPowerKw": 150.0
        }
      ],
      "authMethods": null,
      "paymentMethods": null
    },
    {
      "id": "DEEBWE9089212",
      "connectors": [
        {
          "type": "ccs",
          "maxPowerKw": 150.0
        }
      ],
      "authMethods": null,
      "paymentMethods": null
    },
    {
      "id": "DEEBWE9089213",
      "connectors": [
        {
          "type": "type2",
          "maxPowerKw": 22.0
        }
      ],
      "authMethods": null,
      "paymentMethods": null
    }
  ],
  "facilities": null,
  "address": {
    "city": "Dillenburg",
    "street": "Nixböthestraße",
    "houseNumber": null,
    "postcode": "35683",
    "province": null
  },
  "openingHours": {
    "isOpen247": true,
    "regularHours": null
  }
}