{
  "operatorId": "DE*EBW",
  "geohash": "0D7zLffb",
  "name": "Unknown",
  "evses": [
    {
      "id": "DEEBWE9136092",
      "connectors": [
        {
          "type": "ccs",
          "maxPowerKw": 150.0
        }
      ],
      "authMethods": null,
      "paymentMethods": null
    },
    {
      "id": "DEEBWE9136091",
      "connectors": [
        {
          "type": "ccs",
          "maxPowerKw": 150.0
        }
      ],
      "authMethods": null,
      "paymentMethods": null
    },
    {
      "id": "DEEBWE9136101",
      "connectors": [
        {
          "type": "ccs",
          "maxPowerKw": 300.0
        }
      ],
      "authMethods": null,
      "paymentMethods": null
    },
    {
      "id": "DEEBWE9136102",
      "connectors": [
        {
          "type": "ccs",
          "maxPowerKw": 300.0
        }
      ],
      "authMethods": null,
      "paymentMethods": null
    }
  ],
  "facilities": null,
  "address": {
    "city": "Buttenheim",
    "street": "Am Stauch",
    "houseNumber": null,
    "postcode": "96155",
    "province": null
  },
  "openingHours": {
    "isOpen247": false,
    "regularHours": [
      {
        "weekday": 1,
        "periodBegin": {
          "hour": 7,
          "minute": 0
        },
        "periodEnd": {
          "hour": 23,
          "minute": 59
        }
      },
      {
        "weekday": 2,
        "periodBegin": {
          "hour": 7,
          "minute": 0
        },
        "periodEnd": {
          "hour": 23,
          "minute": 59
        }
      },
      {
        "weekday": 3,
        "periodBegin": {
          "hour": 7,
          "minute": 0
        },
        "periodEnd": {
          "hour": 23,
          "minute": 59
        }
      },
      {
        "weekday": 4,
        "periodBegin": {
          "hour": 7,
          "minute": 0
        },
        "periodEnd": {
          "hour": 23,
          "minute": 59
        }
      },
      {
        "weekday": 5,
        "periodBegin": {
          "hour": 7,
          "minute": 0
        },
        "periodEnd": {
          "hour": 23,
          "minute": 59
        }
      },
      {
        "weekday": 6,
        "periodBegin": {
          "hour": 7,
          "minute": 0
        },
        "periodEnd": {
          "hour": 23,
          "minute": 59
        }
      }
    ]
  }
}