{
  "operatorId": "DE*EBW",
  "geohash": "0GmBfsDB",
  "name": "Unknown",
  "evses": [
    {
      "id": "DEEBWE9097123",
      "connectors": [
        {
          "type": "type2",
          "maxPowerKw": 22.0
        }
      ],
      "authMethods": null,
      "paymentMethods": null
    },
    {
      "id": "DEEBWE9097121",
      "connectors": [
        {
          "type": "ccs",
          "maxPowerKw": 150.0
        }
      ],
      "authMethods": null,
      "paymentMethods": null
    },
    {
      "id": "DEEBWE9097122",
      "connectors": [
        {
          "type": "ccs",
          "maxPowerKw": 150.0
        }
      ],
      "authMethods": null,
      "paymentMethods": null
    },
    {
      "id": "DEEBWE9097551",
      "connectors": [
        {
          "type": "ccs",
          "maxPowerKw": 300.0
        }
      ],
      "authMethods": null,
      "paymentMethods": null
    },
    {
      "id": "DEEBWE9097552",
      "connectors": [
        {
          "type": "ccs",
          "maxPowerKw": 300.0
        }
      ],
      "authMethods": null,
      "paymentMethods": null
    }
  ],
  "facilities": null,
  "address": {
    "city": "Breuna",
    "street": "Wolfhager Straße",
    "houseNumber": null,
    "postcode": "34479",
    "province": null
  },
  "openingHours": {
    "isOpen247": true,
    "regularHours": null
  }
}