{
  "operatorId": "DE*EBW",
  "geohash": "0DOzUUWR",
  "name": "Unknown",
  "evses": [
    {
      "id": "DEEBWE9093812",
      "connectors": [
        {
          "type": "ccs",
          "maxPowerKw": 200.0
        }
      ],
      "authMethods": null,
      "paymentMethods": null
    },
    {
      "id": "DEEBWE9093811",
      "connectors": [
        {
          "type": "ccs",
          "maxPowerKw": 200.0
        }
      ],
      "authMethods": null,
      "paymentMethods": null
    },
    {
      "id": "DEEBWE9094181",
      "connectors": [
        {
          "type": "ccs",
          "maxPowerKw": 200.0
        }
      ],
      "authMethods": null,
      "paymentMethods": null
    },
    {
      "id": "DEEBWE9094182",
      "connectors": [
        {
          "type": "ccs",
          "maxPowerKw": 200.0
        }
      ],
      "authMethods": null,
      "paymentMethods": null
    }
  ],
  "facilities": null,
  "address": {
    "city": "Sinzheim",
    "street": "Industriestraße",
    "houseNumber": null,
    "postcode": "76547",
    "province": null
  },
  "openingHours": {
    "isOpen247": true,
    "regularHours": null
  }
}