{
  "operatorId": "DE*EBW",
  "geohash": "0DggzpwK",
  "name": "Unknown",
  "evses": [
    {
      "id": "DEEBWE9038271",
      "connectors": [
        {
          "type": "type2",
          "maxPowerKw": 22.0
        }
      ],
      "authMethods": null,
      "paymentMethods": null
    },
    {
      "id": "DEEBWE9038272",
      "connectors": [
        {
          "type": "type2",
          "maxPowerKw": 22.0
        }
      ],
      "authMethods": null,
      "paymentMethods": null
    }
  ],
  "facilities": null,
  "address": {
    "city": "Aach",
    "street": "Singener Str.",
    "houseNumber": null,
    "postcode": "78267",
    "province": null
  },
  "openingHours": {
    "isOpen247": true,
    "regularHours": null
  }
}