{
  "operatorId": "DE*EBW",
  "geohash": "0G2UKjPC",
  "name": "Unknown",
  "evses": [
    {
      "id": "DEEBWE9039601",
      "connectors": [
        {
          "type": "ccs",
          "maxPowerKw": 300.0
        }
      ],
      "authMethods": null,
      "paymentMethods": null
    },
    {
      "id": "DEEBWE9039602",
      "connectors": [
        {
          "type": "ccs",
          "maxPowerKw": 300.0
        }
      ],
      "authMethods": null,
      "paymentMethods": null
    },
    {
      "id": "DEEBWE9039603",
      "connectors": [
        {
          "type": "chademo",
          "maxPowerKw": 50.0
        }
      ],
      "authMethods": null,
      "paymentMethods": null
    },
    {
      "id": "DEEBWE9039613",
      "connectors": [
        {
          "type": "ccs",
          "maxPowerKw": 50.0
        }
      ],
      "authMethods": null,
      "paymentMethods": null
    },
    {
      "id": "DEEBWE9039611",
      "connectors": [
        {
          "type": "type2",
          "maxPowerKw": 43.0
        }
      ],
      "authMethods": null,
      "paymentMethods": null
    },
    {
      "id": "DEEBWE9039612",
      "connectors": [
        {
          "type": "chademo",
          "maxPowerKw": 50.0
        }
      ],
      "authMethods": null,
      "paymentMethods": null
    }
  ],
  "facilities": null,
  "address": {
    "city": "Langwedel",
    "street": "A27, Raststätte Goldbach Süd",
    "houseNumber": null,
    "postcode": "27299",
    "province": null
  },
  "openingHours": {
    "isOpen247": true,
    "regularHours": null
  }
}