{
  "operatorId": "DE*EBW",
  "geohash": "0Drqt91Y",
  "name": "Unknown",
  "evses": [
    {
      "id": "DEEBWE9051971",
      "connectors": [
        {
          "type": "type2",
          "maxPowerKw": 43.0
        }
      ],
      "authMethods": null,
      "paymentMethods": null
    },
    {
      "id": "DEEBWE9051972",
      "connectors": [
        {
          "type": "chademo",
          "maxPowerKw": 50.0
        }
      ],
      "authMethods": null,
      "paymentMethods": null
    },
    {
      "id": "DEEBWE9051973",
      "connectors": [
        {
          "type": "ccs",
          "maxPowerKw": 50.0
        }
      ],
      "authMethods": null,
      "paymentMethods": null
    }
  ],
  "facilities": null,
  "address": {
    "city": "Fürstenfeldbruck",
    "street": "Nicolaus-Otto-Str.",
    "houseNumber": null,
    "postcode": "82256",
    "province": null
  },
  "openingHours": {
    "isOpen247": true,
    "regularHours": null
  }
}