{
  "operatorId": "DE*EBW",
  "geohash": "0Dtj76~b",
  "name": "Unknown",
  "evses": [
    {
      "id": "DEEBWE9056711",
      "connectors": [
        {
          "type": "ccs",
          "maxPowerKw": 75.0
        }
      ],
      "authMethods": null,
      "paymentMethods": null
    },
    {
      "id": "DEEBWE9056712",
      "connectors": [
        {
          "type": "ccs",
          "maxPowerKw": 75.0
        }
      ],
      "authMethods": null,
      "paymentMethods": null
    }
  ],
  "facilities": null,
  "address": {
    "city": "Unterschneidheim",
    "street": "Nordhäuser Str.",
    "houseNumber": null,
    "postcode": "73485",
    "province": null
  },
  "openingHours": {
    "isOpen247": true,
    "regularHours": null
  }
}