{
  "operatorId": "DE*TSL",
  "geohash": "0G00TtwX",
  "name": "Brinkum, Germany",
  "evses": [
    {
      "id": "DETSLE0PDW28",
      "connectors": [
        {
          "type": "ccs",
          "maxPowerKw": 250.0
        }
      ],
      "authMethods": null,
      "paymentMethods": null
    },
    {
      "id": "DETSLE0PDWNX",
      "connectors": [
        {
          "type": "ccs",
          "maxPowerKw": 250.0
        }
      ],
      "authMethods": null,
      "paymentMethods": null
    },
    {
      "id": "DETSLE0PDWUC",
      "connectors": [
        {
          "type": "ccs",
          "maxPowerKw": 250.0
        }
      ],
      "authMethods": null,
      "paymentMethods": null
    },
    {
      "id": "DETSLE0PDW46",
      "connectors": [
        {
          "type": "ccs",
          "maxPowerKw": 250.0
        }
      ],
      "authMethods": null,
      "paymentMethods": null
    },
    {
      "id": "DETSLE0PDXE1",
      "connectors": [
        {
          "type": "ccs",
          "maxPowerKw": 250.0
        }
      ],
      "authMethods": null,
      "paymentMethods": null
    },
    {
      "id": "DETSLE0PDVW9",
      "connectors": [
        {
          "type": "ccs",
          "maxPowerKw": 250.0
        }
      ],
      "authMethods": null,
      "paymentMethods": null
    },
    {
      "id": "DETSLE0PDVZB",
      "connectors": [
        {
          "type": "ccs",
          "maxPowerKw": 250.0
        }
      ],
      "authMethods": null,
      "paymentMethods": null
    },
    {
      "id": "DETSLE0PDWD2",
      "connectors": [
        {
          "type": "ccs",
          "maxPowerKw": 250.0
        }
      ],
      "authMethods": null,
      "paymentMethods": null
    },
    {
      "id": "DETSLE0PDWPR",
      "connectors": [
        {
          "type": "ccs",
          "maxPowerKw": 250.0
        }
      ],
      "authMethods": null,
      "paymentMethods": null
    },
    {
      "id": "DETSLE0PDX7S",
      "connectors": [
        {
          "type": "ccs",
          "maxPowerKw": 250.0
        }
      ],
      "authMethods": null,
      "paymentMethods": null
    },
    {
      "id": "DETSLE0PDV63",
      "connectors": [
        {
          "type": "ccs",
          "maxPowerKw": 250.0
        }
      ],
      "authMethods": null,
      "paymentMethods": null
    },
    {
      "id": "DETSLE0PDX48",
      "connectors": [
        {
          "type": "ccs",
          "maxPowerKw": 250.0
        }
      ],
      "authMethods": null,
      "paymentMethods": null
    },
    {
      "id": "DETSLE0PDWYE",
      "connectors": [
        {
          "type": "ccs",
          "maxPowerKw": 250.0
        }
      ],
      "authMethods": null,
      "paymentMethods": null
    },
    {
      "id": "DETSLE1WKP2E",
      "connectors": [
        {
          "type": "ccs",
          "maxPowerKw": 250.0
        }
      ],
      "authMethods": null,
      "paymentMethods": null
    }
  ],
  "facilities": null,
  "address": {
    "city": "Stuhr",
    "street": "Bremer Strasse",
    "houseNumber": null,
    "postcode": "28816",
    "province": null
  },
  "openingHours": {
    "isOpen247": true,
    "regularHours": null
  }
}