{
  "operatorId": "DE*TSL",
  "geohash": "0DrbmWpj",
  "name": "Augsburg, Germany - Oberhausen",
  "evses": [
    {
      "id": "DETSLE00I3PS",
      "connectors": [
        {
          "type": "ccs",
          "maxPowerKw": 250.0
        }
      ],
      "authMethods": null,
      "paymentMethods": null
    },
    {
      "id": "DETSLE00I0A3",
      "connectors": [
        {
          "type": "ccs",
          "maxPowerKw": 250.0
        }
      ],
      "authMethods": null,
      "paymentMethods": null
    },
    {
      "id": "DETSLE00I3Q6",
      "connectors": [
        {
          "type": "ccs",
          "maxPowerKw": 250.0
        }
      ],
      "authMethods": null,
      "paymentMethods": null
    },
    {
      "id": "DETSLE00I3QL",
      "connectors": [
        {
          "type": "ccs",
          "maxPowerKw": 250.0
        }
      ],
      "authMethods": null,
      "paymentMethods": null
    },
    {
      "id": "DETSLE00I3TC",
      "connectors": [
        {
          "type": "ccs",
          "maxPowerKw": 250.0
        }
      ],
      "authMethods": null,
      "paymentMethods": null
    },
    {
      "id": "DETSLE00I3UK",
      "connectors": [
        {
          "type": "ccs",
          "maxPowerKw": 250.0
        }
      ],
      "authMethods": null,
      "paymentMethods": null
    },
    {
      "id": "DETSLE00I0A7",
      "connectors": [
        {
          "type": "ccs",
          "maxPowerKw": 250.0
        }
      ],
      "authMethods": null,
      "paymentMethods": null
    },
    {
      "id": "DETSLE00I0A5",
      "connectors": [
        {
          "type": "ccs",
          "maxPowerKw": 250.0
        }
      ],
      "authMethods": null,
      "paymentMethods": null
    },
    {
      "id": "DETSLE00I3QD",
      "connectors": [
        {
          "type": "ccs",
          "maxPowerKw": 250.0
        }
      ],
      "authMethods": null,
      "paymentMethods": null
    },
    {
      "id": "DETSLE00I0A9",
      "connectors": [
        {
          "type": "ccs",
          "maxPowerKw": 250.0
        }
      ],
      "authMethods": null,
      "paymentMethods": null
    },
    {
      "id": "DETSLE00I3TM",
      "connectors": [
        {
          "type": "ccs",
          "maxPowerKw": 250.0
        }
      ],
      "authMethods": null,
      "paymentMethods": null
    },
    {
      "id": "DETSLE00I3TX",
      "connectors": [
        {
          "type": "ccs",
          "maxPowerKw": 250.0
        }
      ],
      "authMethods": null,
      "paymentMethods": null
    }
  ],
  "facilities": null,
  "address": {
    "city": "Augsburg",
    "street": "Gablinger Weg",
    "houseNumber": null,
    "postcode": "86154",
    "province": null
  },
  "openingHours": {
    "isOpen247": true,
    "regularHours": null
  }
}