{
  "operatorId": "DE*TSL",
  "geohash": "0Da_BSn~",
  "name": "Ludwigshafen, Germany - Oggersheim",
  "evses": [
    {
      "id": "DETSLE0JAE6J",
      "connectors": [
        {
          "type": "ccs",
          "maxPowerKw": 250.0
        }
      ],
      "authMethods": null,
      "paymentMethods": null
    },
    {
      "id": "DETSLE0JAE6M",
      "connectors": [
        {
          "type": "ccs",
          "maxPowerKw": 250.0
        }
      ],
      "authMethods": null,
      "paymentMethods": null
    },
    {
      "id": "DETSLE0JAE6L",
      "connectors": [
        {
          "type": "ccs",
          "maxPowerKw": 250.0
        }
      ],
      "authMethods": null,
      "paymentMethods": null
    },
    {
      "id": "DETSLE0JAE6K",
      "connectors": [
        {
          "type": "ccs",
          "maxPowerKw": 250.0
        }
      ],
      "authMethods": null,
      "paymentMethods": null
    },
    {
      "id": "DETSLE0JAE6U",
      "connectors": [
        {
          "type": "ccs",
          "maxPowerKw": 250.0
        }
      ],
      "authMethods": null,
      "paymentMethods": null
    },
    {
      "id": "DETSLE0JAE6T",
      "connectors": [
        {
          "type": "ccs",
          "maxPowerKw": 250.0
        }
      ],
      "authMethods": null,
      "paymentMethods": null
    },
    {
      "id": "DETSLE0JAE6S",
      "connectors": [
        {
          "type": "ccs",
          "maxPowerKw": 250.0
        }
      ],
      "authMethods": null,
      "paymentMethods": null
    },
    {
      "id": "DETSLE0JAE6R",
      "connectors": [
        {
          "type": "ccs",
          "maxPowerKw": 250.0
        }
      ],
      "authMethods": null,
      "paymentMethods": null
    }
  ],
  "facilities": null,
  "address": {
    "city": "Ludwigshafen am Rhein",
    "street": "Flomersheimer Str.",
    "houseNumber": null,
    "postcode": " 67071 ",
    "province": null
  },
  "openingHours": {
    "isOpen247": true,
    "regularHours": null
  }
}