{
  "operatorId": "DE*TSL",
  "geohash": "0Drzr22X",
  "name": "Dasing, Germany",
  "evses": [
    {
      "id": "DETSLE000Z2P",
      "connectors": [
        {
          "type": "ccs",
          "maxPowerKw": 250.0
        }
      ],
      "authMethods": null,
      "paymentMethods": null
    },
    {
      "id": "DETSLE000Z3B",
      "connectors": [
        {
          "type": "ccs",
          "maxPowerKw": 250.0
        }
      ],
      "authMethods": null,
      "paymentMethods": null
    },
    {
      "id": "DETSLE000Z2Z",
      "connectors": [
        {
          "type": "ccs",
          "maxPowerKw": 250.0
        }
      ],
      "authMethods": null,
      "paymentMethods": null
    },
    {
      "id": "DETSLE000Z2R",
      "connectors": [
        {
          "type": "ccs",
          "maxPowerKw": 250.0
        }
      ],
      "authMethods": null,
      "paymentMethods": null
    },
    {
      "id": "DETSLE000Z31",
      "connectors": [
        {
          "type": "ccs",
          "maxPowerKw": 250.0
        }
      ],
      "authMethods": null,
      "paymentMethods": null
    },
    {
      "id": "DETSLE000Z37",
      "connectors": [
        {
          "type": "ccs",
          "maxPowerKw": 250.0
        }
      ],
      "authMethods": null,
      "paymentMethods": null
    },
    {
      "id": "DETSLE000Z2V",
      "connectors": [
        {
          "type": "ccs",
          "maxPowerKw": 250.0
        }
      ],
      "authMethods": null,
      "paymentMethods": null
    },
    {
      "id": "DETSLE000Z3H",
      "connectors": [
        {
          "type": "ccs",
          "maxPowerKw": 250.0
        }
      ],
      "authMethods": null,
      "paymentMethods": null
    },
    {
      "id": "DETSLE000Z2N",
      "connectors": [
        {
          "type": "ccs",
          "maxPowerKw": 250.0
        }
      ],
      "authMethods": null,
      "paymentMethods": null
    },
    {
      "id": "DETSLE000Z39",
      "connectors": [
        {
          "type": "ccs",
          "maxPowerKw": 250.0
        }
      ],
      "authMethods": null,
      "paymentMethods": null
    },
    {
      "id": "DETSLE000Z2X",
      "connectors": [
        {
          "type": "ccs",
          "maxPowerKw": 250.0
        }
      ],
      "authMethods": null,
      "paymentMethods": null
    },
    {
      "id": "DETSLE000Z33",
      "connectors": [
        {
          "type": "ccs",
          "maxPowerKw": 250.0
        }
      ],
      "authMethods": null,
      "paymentMethods": null
    },
    {
      "id": "DETSLE000Z3D",
      "connectors": [
        {
          "type": "ccs",
          "maxPowerKw": 250.0
        }
      ],
      "authMethods": null,
      "paymentMethods": null
    },
    {
      "id": "DETSLE000Z35",
      "connectors": [
        {
          "type": "ccs",
          "maxPowerKw": 250.0
        }
      ],
      "authMethods": null,
      "paymentMethods": null
    },
    {
      "id": "DETSLE000Z2T",
      "connectors": [
        {
          "type": "ccs",
          "maxPowerKw": 250.0
        }
      ],
      "authMethods": null,
      "paymentMethods": null
    },
    {
      "id": "DETSLE000Z3F",
      "connectors": [
        {
          "type": "ccs",
          "maxPowerKw": 250.0
        }
      ],
      "authMethods": null,
      "paymentMethods": null
    }
  ],
  "facilities": null,
  "address": {
    "city": "Dasing",
    "street": "An d. Brandleiten",
    "houseNumber": null,
    "postcode": "86453",
    "province": null
  },
  "openingHours": {
    "isOpen247": true,
    "regularHours": null
  }
}