{
  "operatorId": "PL*1SN",
  "geohash": "0OPjbQDW",
  "name": "aleja Tadeusza Kościuszki 128, 90-451 Łódź",
  "evses": [
    {
      "id": "PL1SNE69C57FDF",
      "connectors": [
        {
          "type": "type2",
          "maxPowerKw": 22.0
        }
      ],
      "authMethods": null,
      "paymentMethods": null
    },
    {
      "id": "PL1SNE45007B75",
      "connectors": [
        {
          "type": "type2",
          "maxPowerKw": 22.0
        }
      ],
      "authMethods": null,
      "paymentMethods": null
    }
  ],
  "facilities": [
    "energy"
  ],
  "address": {
    "city": "Łódź",
    "street": "aleja Tadeusza Kościuszki",
    "houseNumber": "128",
    "postcode": "90-451",
    "province": null
  },
  "openingHours": {
    "isOpen247": false,
    "regularHours": [
      {
        "weekday": 1,
        "periodBegin": {
          "hour": 0,
          "minute": 0
        },
        "periodEnd": {
          "hour": 23,
          "minute": 59
        }
      },
      {
        "weekday": 2,
        "periodBegin": {
          "hour": 0,
          "minute": 0
        },
        "periodEnd": {
          "hour": 23,
          "minute": 59
        }
      },
      {
        "weekday": 3,
        "periodBegin": {
          "hour": 0,
          "minute": 0
        },
        "periodEnd": {
          "hour": 23,
          "minute": 59
        }
      },
      {
        "weekday": 4,
        "periodBegin": {
          "hour": 0,
          "minute": 0
        },
        "periodEnd": {
          "hour": 23,
          "minute": 59
        }
      },
      {
        "weekday": 5,
        "periodBegin": {
          "hour": 0,
          "minute": 0
        },
        "periodEnd": {
          "hour": 23,
          "minute": 59
        }
      },
      {
        "weekday": 6,
        "periodBegin": {
          "hour": 0,
          "minute": 0
        },
        "periodEnd": {
          "hour": 23,
          "minute": 59
        }
      },
      {
        "weekday": 7,
        "periodBegin": {
          "hour": 0,
          "minute": 0
        },
        "periodEnd": {
          "hour": 23,
          "minute": 59
        }
      }
    ]
  }
}