{
  "operatorId": "PL*8BA",
  "geohash": "0Ojrue4l",
  "name": "księdza Kardynała Stefana Wyszyńskiego 14, 27-200 Starachowice",
  "evses": [
    {
      "id": "PL8BAE82FAAC34",
      "connectors": [
        {
          "type": "type2",
          "maxPowerKw": 22.0
        }
      ],
      "authMethods": null,
      "paymentMethods": null
    },
    {
      "id": "PL8BAE707A4039",
      "connectors": [
        {
          "type": "type2",
          "maxPowerKw": 22.0
        }
      ],
      "authMethods": null,
      "paymentMethods": null
    }
  ],
  "facilities": [
    "energy"
  ],
  "address": {
    "city": "Starachowice",
    "street": "księdza Kardynała Stefana Wyszyńskiego",
    "houseNumber": "14",
    "postcode": "27-200",
    "province": null
  },
  "openingHours": null
}