{
  "operatorId": "PL*9W5",
  "geohash": "0PNI0byd",
  "name": "Morska 80, Gdynia Ogólnodostępna",
  "evses": [
    {
      "id": "PL9W5E11717584",
      "connectors": [
        {
          "type": "type2",
          "maxPowerKw": 22.0
        }
      ],
      "authMethods": null,
      "paymentMethods": null
    }
  ],
  "facilities": [
    "energy"
  ],
  "address": {
    "city": "Gdynia",
    "street": "Morska 80",
    "houseNumber": "_",
    "postcode": "81-225",
    "province": null
  },
  "openingHours": {
    "isOpen247": false,
    "regularHours": [
      {
        "weekday": 1,
        "periodBegin": {
          "hour": 7,
          "minute": 0
        },
        "periodEnd": {
          "hour": 18,
          "minute": 0
        }
      },
      {
        "weekday": 2,
        "periodBegin": {
          "hour": 7,
          "minute": 0
        },
        "periodEnd": {
          "hour": 18,
          "minute": 0
        }
      },
      {
        "weekday": 3,
        "periodBegin": {
          "hour": 7,
          "minute": 0
        },
        "periodEnd": {
          "hour": 18,
          "minute": 0
        }
      },
      {
        "weekday": 4,
        "periodBegin": {
          "hour": 7,
          "minute": 0
        },
        "periodEnd": {
          "hour": 18,
          "minute": 0
        }
      },
      {
        "weekday": 5,
        "periodBegin": {
          "hour": 7,
          "minute": 0
        },
        "periodEnd": {
          "hour": 18,
          "minute": 0
        }
      },
      {
        "weekday": 6,
        "periodBegin": {
          "hour": 7,
          "minute": 0
        },
        "periodEnd": {
          "hour": 14,
          "minute": 0
        }
      }
    ]
  }
}