{
  "operatorId": "PL*BY4",
  "geohash": "0O4WFGmz",
  "name": "Centrum Multi-Medica w Zielonce",
  "evses": [
    {
      "id": "PLBY4ECEA00541",
      "connectors": [
        {
          "type": "type2",
          "maxPowerKw": 11.0
        }
      ],
      "authMethods": null,
      "paymentMethods": null
    },
    {
      "id": "PLBY4ECEA00301",
      "connectors": [
        {
          "type": "type2",
          "maxPowerKw": 11.0
        }
      ],
      "authMethods": null,
      "paymentMethods": null
    }
  ],
  "facilities": [
    "energy"
  ],
  "address": {
    "city": "Zielonka",
    "street": "Józefa Poniatowskiego",
    "houseNumber": "97",
    "postcode": "05-220",
    "province": null
  },
  "openingHours": {
    "isOpen247": false,
    "regularHours": [
      {
        "weekday": 1,
        "periodBegin": {
          "hour": 0,
          "minute": 0
        },
        "periodEnd": {
          "hour": 23,
          "minute": 59
        }
      },
      {
        "weekday": 2,
        "periodBegin": {
          "hour": 0,
          "minute": 0
        },
        "periodEnd": {
          "hour": 23,
          "minute": 59
        }
      },
      {
        "weekday": 3,
        "periodBegin": {
          "hour": 0,
          "minute": 0
        },
        "periodEnd": {
          "hour": 23,
          "minute": 59
        }
      },
      {
        "weekday": 4,
        "periodBegin": {
          "hour": 0,
          "minute": 0
        },
        "periodEnd": {
          "hour": 23,
          "minute": 59
        }
      },
      {
        "weekday": 5,
        "periodBegin": {
          "hour": 0,
          "minute": 0
        },
        "periodEnd": {
          "hour": 23,
          "minute": 59
        }
      },
      {
        "weekday": 6,
        "periodBegin": {
          "hour": 0,
          "minute": 0
        },
        "periodEnd": {
          "hour": 23,
          "minute": 59
        }
      },
      {
        "weekday": 7,
        "periodBegin": {
          "hour": 0,
          "minute": 0
        },
        "periodEnd": {
          "hour": 23,
          "minute": 59
        }
      }
    ]
  }
}