{
  "operatorId": "PL*GJC",
  "geohash": "0OQXk3H3",
  "name": "Hotel Biały Dom",
  "evses": [
    {
      "id": "PLGJCEEVP01891",
      "connectors": [
        {
          "type": "type2",
          "maxPowerKw": 11.0
        }
      ],
      "authMethods": null,
      "paymentMethods": null
    },
    {
      "id": "PLGJCEEVP01892",
      "connectors": [
        {
          "type": "type2",
          "maxPowerKw": 11.0
        }
      ],
      "authMethods": null,
      "paymentMethods": null
    }
  ],
  "facilities": [
    "energy"
  ],
  "address": {
    "city": "Poznań",
    "street": "Spławie",
    "houseNumber": "43A",
    "postcode": "61-312",
    "province": null
  },
  "openingHours": null
}