{
  "operatorId": "PL*GN6",
  "geohash": "0L_NOtE8",
  "name": "GG AUTO RZESZÓW VW",
  "evses": [
    {
      "id": "PLGN6E38E7MZPR",
      "connectors": [
        {
          "type": "type2",
          "maxPowerKw": 22.0
        }
      ],
      "authMethods": null,
      "paymentMethods": null
    },
    {
      "id": "PLGN6E01893119",
      "connectors": [
        {
          "type": "ccs",
          "maxPowerKw": 22.0
        }
      ],
      "authMethods": null,
      "paymentMethods": null
    }
  ],
  "facilities": [
    "energy"
  ],
  "address": {
    "city": "Rzeszów",
    "street": "Lubelska 50E",
    "houseNumber": "_",
    "postcode": "35-233",
    "province": null
  },
  "openingHours": {
    "isOpen247": false,
    "regularHours": [
      {
        "weekday": 1,
        "periodBegin": {
          "hour": 7,
          "minute": 0
        },
        "periodEnd": {
          "hour": 18,
          "minute": 0
        }
      },
      {
        "weekday": 2,
        "periodBegin": {
          "hour": 7,
          "minute": 0
        },
        "periodEnd": {
          "hour": 18,
          "minute": 0
        }
      },
      {
        "weekday": 3,
        "periodBegin": {
          "hour": 7,
          "minute": 0
        },
        "periodEnd": {
          "hour": 18,
          "minute": 0
        }
      },
      {
        "weekday": 4,
        "periodBegin": {
          "hour": 7,
          "minute": 0
        },
        "periodEnd": {
          "hour": 18,
          "minute": 0
        }
      },
      {
        "weekday": 5,
        "periodBegin": {
          "hour": 7,
          "minute": 0
        },
        "periodEnd": {
          "hour": 18,
          "minute": 0
        }
      },
      {
        "weekday": 6,
        "periodBegin": {
          "hour": 9,
          "minute": 0
        },
        "periodEnd": {
          "hour": 15,
          "minute": 0
        }
      }
    ]
  }
}