{
  "operatorId": "PL*GWN",
  "geohash": "0M4Q5lxr",
  "name": "Basen Miejski Świewoda Świebodzin",
  "evses": [
    {
      "id": "PLGWNE26599802",
      "connectors": [
        {
          "type": "type2",
          "maxPowerKw": 22.0
        }
      ],
      "authMethods": null,
      "paymentMethods": null
    },
    {
      "id": "PLGWNE26599801",
      "connectors": [
        {
          "type": "ccs",
          "maxPowerKw": 120.0
        }
      ],
      "authMethods": null,
      "paymentMethods": null
    },
    {
      "id": "PLGWNE26599803",
      "connectors": [
        {
          "type": "ccs",
          "maxPowerKw": 120.0
        }
      ],
      "authMethods": null,
      "paymentMethods": null
    },
    {
      "id": "PLGWNE26904002",
      "connectors": [
        {
          "type": "type2",
          "maxPowerKw": 22.0
        }
      ],
      "authMethods": null,
      "paymentMethods": null
    },
    {
      "id": "PLGWNE26904001",
      "connectors": [
        {
          "type": "ccs",
          "maxPowerKw": 150.0
        }
      ],
      "authMethods": null,
      "paymentMethods": null
    },
    {
      "id": "PLGWNE26904003",
      "connectors": [
        {
          "type": "ccs",
          "maxPowerKw": 150.0
        }
      ],
      "authMethods": null,
      "paymentMethods": null
    }
  ],
  "facilities": [
    "energy"
  ],
  "address": {
    "city": "Świebodzin",
    "street": "Sulechowska",
    "houseNumber": "6",
    "postcode": "66-200",
    "province": null
  },
  "openingHours": {
    "isOpen247": false,
    "regularHours": [
      {
        "weekday": 1,
        "periodBegin": {
          "hour": 0,
          "minute": 0
        },
        "periodEnd": {
          "hour": 23,
          "minute": 59
        }
      },
      {
        "weekday": 2,
        "periodBegin": {
          "hour": 0,
          "minute": 0
        },
        "periodEnd": {
          "hour": 23,
          "minute": 59
        }
      },
      {
        "weekday": 3,
        "periodBegin": {
          "hour": 0,
          "minute": 0
        },
        "periodEnd": {
          "hour": 23,
          "minute": 59
        }
      },
      {
        "weekday": 4,
        "periodBegin": {
          "hour": 0,
          "minute": 0
        },
        "periodEnd": {
          "hour": 23,
          "minute": 59
        }
      },
      {
        "weekday": 5,
        "periodBegin": {
          "hour": 0,
          "minute": 0
        },
        "periodEnd": {
          "hour": 23,
          "minute": 59
        }
      },
      {
        "weekday": 6,
        "periodBegin": {
          "hour": 0,
          "minute": 0
        },
        "periodEnd": {
          "hour": 23,
          "minute": 59
        }
      },
      {
        "weekday": 7,
        "periodBegin": {
          "hour": 0,
          "minute": 0
        },
        "periodEnd": {
          "hour": 23,
          "minute": 59
        }
      }
    ]
  }
}