{
  "operatorId": "PL*JMG",
  "geohash": "0OWgD1l8",
  "name": "Kasztanowa 16, 88-306 Dąbrowa",
  "evses": [
    {
      "id": "PLJMGEAC1DDFC5",
      "connectors": [
        {
          "type": "type2",
          "maxPowerKw": 22.0
        }
      ],
      "authMethods": null,
      "paymentMethods": null
    },
    {
      "id": "PLJMGE92D3779A",
      "connectors": [
        {
          "type": "type2",
          "maxPowerKw": 22.0
        }
      ],
      "authMethods": null,
      "paymentMethods": null
    }
  ],
  "facilities": [
    "energy"
  ],
  "address": {
    "city": "Dąbrowa",
    "street": "Kasztanowa",
    "houseNumber": "16",
    "postcode": "88-306",
    "province": null
  },
  "openingHours": null
}