{
  "operatorId": "PL*Q55",
  "geohash": "0OANScI8",
  "name": "Lidl Strzelin",
  "evses": [
    {
      "id": "PLQ55E01209601",
      "connectors": [],
      "authMethods": null,
      "paymentMethods": null
    },
    {
      "id": "PLQ55E01209602",
      "connectors": [],
      "authMethods": null,
      "paymentMethods": null
    }
  ],
  "facilities": [
    "energy"
  ],
  "address": {
    "city": "Strzelin",
    "street": "Wolności",
    "houseNumber": "7/B",
    "postcode": "57-100",
    "province": null
  },
  "openingHours": null
}