{
  "operatorId": "PL*Q55",
  "geohash": "0M7jerU1",
  "name": "Lidl Tarnowo Podgórne",
  "evses": [
    {
      "id": "PLQ55E01151001",
      "connectors": [],
      "authMethods": null,
      "paymentMethods": null
    },
    {
      "id": "PLQ55E01151002",
      "connectors": [],
      "authMethods": null,
      "paymentMethods": null
    }
  ],
  "facilities": [
    "energy"
  ],
  "address": {
    "city": "Tarnowo Podgórne",
    "street": "Poznańska",
    "houseNumber": "135",
    "postcode": "62-080",
    "province": null
  },
  "openingHours": null
}