{
  "operatorId": "PL*UFC",
  "geohash": "0LzK50rh",
  "name": "EDRI Agata Meble, Nowy Sącz",
  "evses": [
    {
      "id": "PLUFCE79224627",
      "connectors": [
        {
          "type": "ccs",
          "maxPowerKw": 400.0
        }
      ],
      "authMethods": null,
      "paymentMethods": null
    },
    {
      "id": "PLUFCE70524628",
      "connectors": [
        {
          "type": "ccs",
          "maxPowerKw": 400.0
        }
      ],
      "authMethods": null,
      "paymentMethods": null
    },
    {
      "id": "PLUFCE14624629",
      "connectors": [
        {
          "type": "ccs",
          "maxPowerKw": 200.0
        }
      ],
      "authMethods": null,
      "paymentMethods": null
    },
    {
      "id": "PLUFCE40824630",
      "connectors": [
        {
          "type": "ccs",
          "maxPowerKw": 200.0
        }
      ],
      "authMethods": null,
      "paymentMethods": null
    },
    {
      "id": "PLUFCE11824631",
      "connectors": [
        {
          "type": "ccs",
          "maxPowerKw": 300.0
        }
      ],
      "authMethods": null,
      "paymentMethods": null
    },
    {
      "id": "PLUFCE41124632",
      "connectors": [
        {
          "type": "ccs",
          "maxPowerKw": 300.0
        }
      ],
      "authMethods": null,
      "paymentMethods": null
    }
  ],
  "facilities": [
    "energy"
  ],
  "address": {
    "city": "Nowy Sącz",
    "street": "Jeremiego Wiśniowieckiego",
    "houseNumber": "138",
    "postcode": "33-300",
    "province": null
  },
  "openingHours": {
    "isOpen247": false,
    "regularHours": [
      {
        "weekday": 1,
        "periodBegin": {
          "hour": 0,
          "minute": 0
        },
        "periodEnd": {
          "hour": 23,
          "minute": 59
        }
      },
      {
        "weekday": 2,
        "periodBegin": {
          "hour": 0,
          "minute": 0
        },
        "periodEnd": {
          "hour": 23,
          "minute": 59
        }
      },
      {
        "weekday": 3,
        "periodBegin": {
          "hour": 0,
          "minute": 0
        },
        "periodEnd": {
          "hour": 23,
          "minute": 59
        }
      },
      {
        "weekday": 4,
        "periodBegin": {
          "hour": 0,
          "minute": 0
        },
        "periodEnd": {
          "hour": 23,
          "minute": 59
        }
      },
      {
        "weekday": 5,
        "periodBegin": {
          "hour": 0,
          "minute": 0
        },
        "periodEnd": {
          "hour": 23,
          "minute": 59
        }
      },
      {
        "weekday": 6,
        "periodBegin": {
          "hour": 0,
          "minute": 0
        },
        "periodEnd": {
          "hour": 23,
          "minute": 59
        }
      },
      {
        "weekday": 7,
        "periodBegin": {
          "hour": 0,
          "minute": 0
        },
        "periodEnd": {
          "hour": 23,
          "minute": 59
        }
      }
    ]
  }
}