{
  "operatorId": "PL*UJM",
  "geohash": "0ORIwIOQ",
  "name": "HORTENSJA SP. Z O.O.",
  "evses": [
    {
      "id": "PLUJME20242024",
      "connectors": [],
      "authMethods": null,
      "paymentMethods": null
    },
    {
      "id": "PLUJME20242025",
      "connectors": [],
      "authMethods": null,
      "paymentMethods": null
    }
  ],
  "facilities": [
    "energy"
  ],
  "address": {
    "city": "JASIN",
    "street": "POZNAŃSKA",
    "houseNumber": "6",
    "postcode": "62-020",
    "province": null
  },
  "openingHours": null
}