{
  "operatorId": "PL*XGY",
  "geohash": "0OiZBc17",
  "name": "Skoda Autorud Kielce",
  "evses": [
    {
      "id": "PLXGYE13040011",
      "connectors": [
        {
          "type": "ccs",
          "maxPowerKw": 60.0
        }
      ],
      "authMethods": null,
      "paymentMethods": null
    },
    {
      "id": "PLXGYE13040012",
      "connectors": [
        {
          "type": "ccs",
          "maxPowerKw": 60.0
        }
      ],
      "authMethods": null,
      "paymentMethods": null
    }
  ],
  "facilities": [
    "energy"
  ],
  "address": {
    "city": "Kielce",
    "street": "Krakowska",
    "houseNumber": "283",
    "postcode": "25-801",
    "province": null
  },
  "openingHours": {
    "isOpen247": false,
    "regularHours": [
      {
        "weekday": 1,
        "periodBegin": {
          "hour": 0,
          "minute": 0
        },
        "periodEnd": {
          "hour": 23,
          "minute": 59
        }
      },
      {
        "weekday": 2,
        "periodBegin": {
          "hour": 0,
          "minute": 0
        },
        "periodEnd": {
          "hour": 23,
          "minute": 59
        }
      },
      {
        "weekday": 3,
        "periodBegin": {
          "hour": 0,
          "minute": 0
        },
        "periodEnd": {
          "hour": 23,
          "minute": 59
        }
      },
      {
        "weekday": 4,
        "periodBegin": {
          "hour": 0,
          "minute": 0
        },
        "periodEnd": {
          "hour": 23,
          "minute": 59
        }
      },
      {
        "weekday": 5,
        "periodBegin": {
          "hour": 0,
          "minute": 0
        },
        "periodEnd": {
          "hour": 23,
          "minute": 59
        }
      },
      {
        "weekday": 6,
        "periodBegin": {
          "hour": 0,
          "minute": 0
        },
        "periodEnd": {
          "hour": 23,
          "minute": 59
        }
      },
      {
        "weekday": 7,
        "periodBegin": {
          "hour": 0,
          "minute": 0
        },
        "periodEnd": {
          "hour": 23,
          "minute": 59
        }
      }
    ]
  }
}